indicator/__init__.py
indicator/indicator.py
indicator/searchSourceCode.py
indicator_intelligence-1.0.1.dist-info/LICENSE
indicator_intelligence-1.0.1.dist-info/METADATA
indicator_intelligence-1.0.1.dist-info/WHEEL
indicator_intelligence-1.0.1.dist-info/top_level.txt
indicator_intelligence-1.0.1.dist-info/RECORD
