Metadata-Version: 2.1
Name: indicator-intelligence
Version: 1.0.1
Summary: Indicator Intelligence
Author: OsmanKandemir
Author-email: osmankandemir00@gmail.com
Keywords: python,threat,threat-intelligence,indicator
Classifier: License :: OSI Approved :: MIT License
Classifier: Topic :: Software Development :: Build Tools
Classifier: Programming Language :: Python :: 3.7
Classifier: Programming Language :: Python :: 3.8
Classifier: Programming Language :: Python :: 3.9
Classifier: Programming Language :: Python :: 3.10
Classifier: Programming Language :: Python :: 3 :: Only
Classifier: Operating System :: OS Independent
Requires-Python: >=3.7
License-File: LICENSE
Requires-Dist: beautifulsoup4 (==4.11.2)
Requires-Dist: certifi (==2022.12.7)
Requires-Dist: charset-normalizer (==3.0.1)
Requires-Dist: filelock (==3.9.0)
Requires-Dist: idna (==3.4)
Requires-Dist: platformdirs (==3.0.0)
Requires-Dist: requests (==2.28.2)
Requires-Dist: soupsieve (==2.4)
Requires-Dist: uritools (==4.0.1)
Requires-Dist: urlextract (==1.8.0)
Requires-Dist: urllib3 (==1.26.14)
